dd2nx/__init__.py
dd2nx/test_to_nx.py
dd2nx/to_nx.py
dd2nx-0.1.2.dist-info/WHEEL
dd2nx-0.1.2.dist-info/METADATA
dd2nx-0.1.2.dist-info/RECORD
